LICENSE
README.rst
setup.py
lastcast/__init__.py
lastcast/__main__.py
lastcast.egg-info/PKG-INFO
lastcast.egg-info/SOURCES.txt
lastcast.egg-info/dependency_links.txt
lastcast.egg-info/entry_points.txt
lastcast.egg-info/requires.txt
lastcast.egg-info/top_level.txt