Metadata-Version: 2.1
Name: lastcast
Version: 3.0.0
Summary: Scrobble music to last.fm from Chromecast.
Home-page: https://github.com/erik/lastcast
Author: Erik Price
License: MIT
Classifier: Programming Language :: Python
Classifier: Programming Language :: Python :: 3
Classifier: Operating System :: OS Independent
License-File: LICENSE
